PyxlSql/__init__.py
PyxlSql/pyxlAbstracts.py
PyxlSql/pyxlArgs.py
PyxlSql/pyxlEngine.py
PyxlSql/pyxlErrors.py
PyxlSql/pyxlGrammar.py
PyxlSql/pyxlResults.py
PyxlSql/pyxlSheets.py
PyxlSql/pyxlSql.py
PyxlSql/pyxlStages.py
PyxlSql/pyxlWorkbook.py
open_pyxl_sql-0.12.0.dist-info/LICENCE
open_pyxl_sql-0.12.0.dist-info/METADATA
open_pyxl_sql-0.12.0.dist-info/WHEEL
open_pyxl_sql-0.12.0.dist-info/top_level.txt
open_pyxl_sql-0.12.0.dist-info/RECORD
