Metadata-Version: 2.1
Name: open-pyxl-sql
Version: 0.12.0
Summary: A tiny SQL engine for Excel files, based on Openpyxl
Home-page: https://gitlab.com/fabien.battini/pyxlsql
Author: Fabien BATTINI
Author-email: fabien.battini@gmail.com
Classifier: Programming Language :: Python :: 3
Classifier: License :: OSI Approved :: European Union Public Licence 1.2 (EUPL 1.2)
Classifier: Operating System :: OS Independent
Classifier: Development Status :: 4 - Beta
Classifier: Intended Audience :: End Users/Desktop
Classifier: Topic :: Office/Business :: Office Suites
Requires-Python: >=3.6
License-File: LICENCE
